{
  "5th-class-ppts": [
    {
          "title": "Std 5 പശ്ചാത്തലം",
          "link": "https://drive.google.com/uc?export=download&id=1wWqll7nobguQLi65K5R8NHLLonYBcoZK"     
    },
    {
          "title": "ദൗത്യം 1 എന്റെ നാടിനെ അറിയാം ",
          "link": "https://drive.google.com/uc?export=download&id=17a3HqYeZ6ZDpXRohcTZ-Ks2nH6o_kayV"     
    },
    {
          "title": "ദൗത്യം 2 നാടിനായി എന്തുചെയ്യാം",
          "link": "https://drive.google.com/uc?export=download&id=1vgTySCniaRMmr3PdOI2Fja8VAqE69c75"     
    },
    {
          "title": "ദൗത്യം 3  ജൈവവൈവിധ്യത്തെ എങ്ങനെ നിലനിർത്താം",
          "link": "https://drive.google.com/uc?export=download&id=1jzWozqCyApSAzswMr1Ke_Qxw_wC7vBZS"     
    }
    
  ],
  "6th-class-ppts": [
    {
          "title": "Std 6 പശ്ചാത്തലം",
          "link": "https://drive.google.com/uc?export=download&id=1VibKzHKPQbZ86R4BfztRi-9HLFa3rqF9"     
    },
    {
          "title": "ദൗത്യം 1-പോഷകങ്ങളുടെ രഹസ്യം തേടി",
          "link": "https://drive.google.com/uc?export=download&id=19KqYBujVib-S681yDMLgMMhdFN0m6jBv"     
    },
    {
          "title": "ദൗത്യം 2 ആരോഗ്യത്തിന്റെ പുതിയ വഴികൾ!",
          "link": "https://drive.google.com/uc?export=download&id=1OuDUd1BQuvI0pHViLzSbxNmw5meWb3BF"     
    }
  ],
  "7th-class-ppts": [
    {
          "title": "Std 7 പശ്ചാത്തലം",
          "link": "https://drive.google.com/uc?export=download&id=1WEUYbbwkODkF3bdknCHS9hyZY2UhYZpk"     
    },
    {
          "title": "ദൗത്യം 1 വീടിനേയറിയാം, മാലിന്യ മുക്തമാക്കാം",
          "link": "https://drive.google.com/uc?export=download&id=1umYw7FQGvPRgsGBan1NYUDFiv5sPWrWG"     
    },
    {
          "title": "ദൗത്യം 2 അറിയാം പറയാം ",
          "link": "https://drive.google.com/uc?export=download&id=137JBOdklZSovJuUzG7ynDmhwUxgHCHmH"     
    },
    {
          "title": "ദൗത്യം 3 നിയമനിർമ്മാണത്തിലേക്ക്",
          "link": "https://drive.google.com/uc?export=download&id=1Lb5kaEABeLB_fc9enSKVl7Z1pP3IIWYz"     
    }
  ]
}
